fastlangid/__init__.py
fastlangid/langid.py
fastlangid/regex_rule.py
fastlangid/utils.py
fastlangid/models/lid.176.ftz
fastlangid/models/model_s.ftz
fastlangid/models/punc.dict
fastlangid/models/unicode_lang.dict
fastlangid-1.0.11.dist-info/LICENSE
fastlangid-1.0.11.dist-info/METADATA
fastlangid-1.0.11.dist-info/WHEEL
fastlangid-1.0.11.dist-info/top_level.txt
fastlangid-1.0.11.dist-info/RECORD
