Metadata-Version: 2.1
Name: fastlangid
Version: 1.0.11
Summary: Language detection for news powered by fasttext
Home-page: https://github.com/currentsapi/fastlangid
Author: Ray
Author-email: ray@currentsapi.services
License: Apache License 2.0
Keywords: language detection library
Platform: UNKNOWN
Classifier: Development Status :: 5 - Production/Stable
Classifier: Intended Audience :: Developers
Classifier: License :: OSI Approved :: Apache Software License
Classifier: Operating System :: OS Independent
Classifier: Programming Language :: Python :: 3
Classifier: Programming Language :: Python :: 3.4
Classifier: Programming Language :: Python :: 3.5
Classifier: Programming Language :: Python :: 3.6
Classifier: Programming Language :: Python :: 3.7
Classifier: Programming Language :: Python :: 3.8
Classifier: Programming Language :: Python :: 3.9
Requires-Dist: fasttext
